{
  "project_info": {
    "project_number": "201510791880",
    "project_id": "notificationapp-bf239",
    "storage_bucket": "notificationapp-bf239.appspot.com"
  },
  "client": [
    {
      "client_info": {
        "mobilesdk_app_id": "1:201510791880:android:b46c013648a9c0d4dbd3fd",
        "android_client_info": {
          "package_name": "com.notificationapp"
        }
      },
      "oauth_client": [],
      "api_key": [
        {
          "current_key": "AIzaSyAlGgxXslM0Jnj3alS5uYCvhlWu3yMnzzI"
        }
      ],
      "services": {
        "appinvite_service": {
          "other_platform_oauth_client": []
        }
      }
    }
  ],
  "configuration_version": "1"
}